setup.py
radicals.egg-info/PKG-INFO
radicals.egg-info/SOURCES.txt
radicals.egg-info/dependency_links.txt
radicals.egg-info/not-zip-safe
radicals.egg-info/top_level.txt
user/__init__.py