Metadata-Version: 1.0
Name: radicals
Version: 0.1
Summary: The hilarious joke in the world
Home-page: UNKNOWN
Author: Hilarious Radical
Author-email: anirudha.sathe@exadatum.com
License: Exadatum
Platform: UNKNOWN
